LICENSE.txt
MANIFEST.in
README.rst
pyproject.toml
setup.cfg
setup.py
teachcompute/__init__.py
teachcompute/ext_test_case.py
teachcompute.egg-info/PKG-INFO
teachcompute.egg-info/SOURCES.txt
teachcompute.egg-info/dependency_links.txt
teachcompute.egg-info/requires.txt
teachcompute.egg-info/top_level.txt
teachcompute/datasets/__init__.py
teachcompute/datasets/eurostat.py
teachcompute/fctmr/__init__.py
teachcompute/fctmr/fast_parallel_fctmr.py
teachcompute/fctmr/pyparallel_fctmr.py
teachcompute/fctmr/simplefctmr.py